{"repository":"https://raw.github.com/sparkfun/L6470-AutoDriver/75f05622a3c4cb8d3287ef6653b09308f30772d7/Hardware/L6470 AutoDriver.brd",
"resolution":"600",
"outline_layer":"20",
"silk_layer":"place",
"no_parts":0,
"no_images":0,
"skip_vias":0,
"thickness":1.6,
"board_color":"0x98041C",
"trace_color":"0xE2012D",
"plating":"silver",
"silk":"ivory",
"component_packages": [{"name":"0402-CAP","value":"0.1uF"},{"name":"EIA3216","value":"10uF"},{"name":"PANASONIC_H13","value":"100uF"},{"name":"0402-CAP","value":"0.22uF"},{"name":"0402-CAP","value":"10nF"},{"name":"EIA3528","value":"47uF"},{"name":"SOT23","value":"BAV99"},{"name":"MICRO-FIDUCIAL","value":"FIDUCIALUFIDUCIAL"},{"name":"2X5-SHROUDED","value":"M05X2SHD"},{"name":"0402-RES","value":"10k"},{"name":"0402-RES","value":"100"},{"name":"3362U","value":"200k"},{"name":"0402-RES","value":"8.2k"},{"name":"0402-RES","value":"33k"},{"name":"2PT_GND_TIE","value":"2PT_GND_TIE"},{"name":"STAND-OFF","value":"STAND-OFF"},{"name":"FOUR_LAYER_WARNING","value":"FOUR_LAYER_WARNING"},{"name":"HTSSOP28","value":"L6470 "}]}